prompt2slip/__init__.py
prompt2slip/base_attacker.py
prompt2slip/calc_loss.py
prompt2slip/loss_transformers.py
prompt2slip/transformers_attacker.py
prompt2slip/utils.py
prompt2slip-1.0.0.dist-info/LICENSE
prompt2slip-1.0.0.dist-info/WHEEL
prompt2slip-1.0.0.dist-info/METADATA
prompt2slip-1.0.0.dist-info/RECORD
