Metadata-Version: 2.1
Name: prompt2slip
Version: 1.0.0
Summary: 
Author: akiFQC
Author-email: yakaredori@gmail.com
Requires-Python: >=3.8
Classifier: Programming Language :: Python :: 3
Classifier: Programming Language :: Python :: 3.8
Classifier: Programming Language :: Python :: 3.9
Classifier: Programming Language :: Python :: 3.10
Requires-Dist: torch (>=1.10.0,<2.0.0)
Requires-Dist: torchtyping (>=0.1.4,<0.2.0)
Requires-Dist: transformers (>=4.11.3,<5.0.0)
